missmecha/__init__.py
missmecha/analysis.py
missmecha/generator.py
missmecha/impute.py
missmecha/util.py
missmecha/visual.py
missmecha/generate/__init__.py
missmecha/generate/mar.py
missmecha/generate/marcat.py
missmecha/generate/mcar.py
missmecha/generate/mnar.py
missmecha/generate/mnarcat.py
missmecha_py-0.1.2.dist-info/licenses/LICENSE
missmecha_py-0.1.2.dist-info/METADATA
missmecha_py-0.1.2.dist-info/WHEEL
missmecha_py-0.1.2.dist-info/top_level.txt
missmecha_py-0.1.2.dist-info/RECORD
